pyos_info/__init__.py
pyos_info/__main__.py
pyos_info/utils.py
pyos_info-0.0.2.dist-info/METADATA
pyos_info-0.0.2.dist-info/WHEEL
pyos_info-0.0.2.dist-info/entry_points.txt
pyos_info-0.0.2.dist-info/top_level.txt
pyos_info-0.0.2.dist-info/RECORD
