Metadata-Version: 2.1
Name: pyos-info
Version: 0.0.2
Summary: UNKNOWN
Home-page: UNKNOWN
Author: dboyliao
Author-email: qmalliao@gmail.com
License: MIT
Platform: UNKNOWN
Requires-Dist: click
Provides-Extra: dev
Requires-Dist: black ; extra == 'dev'
Requires-Dist: isort ; extra == 'dev'
Requires-Dist: flake8 ; extra == 'dev'
